dewi_kadita/__init__.py
dewi_kadita/cli.py
dewi_kadita/core/__init__.py
dewi_kadita/core/metrics.py
dewi_kadita/core/solver.py
dewi_kadita/core/systems.py
dewi_kadita/io/__init__.py
dewi_kadita/io/config_manager.py
dewi_kadita/io/data_handler.py
dewi_kadita/utils/__init__.py
dewi_kadita/utils/logger.py
dewi_kadita/utils/timer.py
dewi_kadita/visualization/__init__.py
dewi_kadita/visualization/animator.py
dewi_kadita-0.0.4.dist-info/LICENSE
dewi_kadita-0.0.4.dist-info/METADATA
dewi_kadita-0.0.4.dist-info/WHEEL
dewi_kadita-0.0.4.dist-info/entry_points.txt
dewi_kadita-0.0.4.dist-info/RECORD
